plug_mcp/__init__.py
plug_mcp/client.py
plug_mcp/guardrails.py
plug_mcp/transport.py
plug_mcp/utils.py
plug_mcp/llm/__init__.py
plug_mcp/llm/anthropic.py
plug_mcp/llm/openai.py
plug_mcp-0.1.2.dist-info/METADATA
plug_mcp-0.1.2.dist-info/WHEEL
plug_mcp-0.1.2.dist-info/licenses/LICENSE
plug_mcp-0.1.2.dist-info/RECORD
